design.plone.iocittadino-1.0.0b9-py3.11-nspkg.pth
design/plone/iocittadino/__init__.py
design/plone/iocittadino/configure.zcml
design/plone/iocittadino/dependencies.zcml
design/plone/iocittadino/permissions.zcml
design/plone/iocittadino/setuphandlers.py
design/plone/iocittadino/testing.py
design/plone/iocittadino/actions/__init__.py
design/plone/iocittadino/actions/configure.zcml
design/plone/iocittadino/actions/mailfromfield.py
design/plone/iocittadino/adapters/__init__.py
design/plone/iocittadino/adapters/configure.zcml
design/plone/iocittadino/adapters/indexers.py
design/plone/iocittadino/adapters/content_store/__init__.py
design/plone/iocittadino/adapters/content_store/configure.zcml
design/plone/iocittadino/adapters/content_store/message.py
design/plone/iocittadino/adapters/content_store/pratica.py
design/plone/iocittadino/adapters/content_store/types.py
design/plone/iocittadino/adapters/content_store/user.py
design/plone/iocittadino/adapters/content_store/mixins/__init__.py
design/plone/iocittadino/adapters/content_store/mixins/current_user.py
design/plone/iocittadino/behaviors/__init__.py
design/plone/iocittadino/behaviors/configure.zcml
design/plone/iocittadino/behaviors/constrains.py
design/plone/iocittadino/browser/__init__.py
design/plone/iocittadino/browser/configure.zcml
design/plone/iocittadino/browser/mail.py
design/plone/iocittadino/browser/download/__init__.py
design/plone/iocittadino/browser/download/configure.zcml
design/plone/iocittadino/browser/download/download.py
design/plone/iocittadino/browser/download/download_traversers.py
design/plone/iocittadino/browser/static/.gitkeep
design/plone/iocittadino/browser/templates/mail/mail.pt
design/plone/iocittadino/content/__init__.py
design/plone/iocittadino/content/modello_pratica.py
design/plone/iocittadino/data_store/__init__.py
design/plone/iocittadino/data_store/configure.zcml
design/plone/iocittadino/data_store/soup/__init__.py
design/plone/iocittadino/data_store/soup/blob_storage.py
design.plone.iocittadino-1.0.0b9.dist-info/LICENSE.GPL
design.plone.iocittadino-1.0.0b9.dist-info/LICENSE.rst
design.plone.iocittadino-1.0.0b9.dist-info/METADATA
design.plone.iocittadino-1.0.0b9.dist-info/WHEEL
design.plone.iocittadino-1.0.0b9.dist-info/entry_points.txt
design.plone.iocittadino-1.0.0b9.dist-info/namespace_packages.txt
design.plone.iocittadino-1.0.0b9.dist-info/top_level.txt
design.plone.iocittadino-1.0.0b9.dist-info/RECORD
