Metadata-Version: 2.1
Name: design.plone.iocittadino
Version: 1.0.0b9
Summary: An add-on for Plone
Home-page: https://gitlab.com/redturtle/io-comune/design.plone.iocittadino
Author: RedTurtle
Author-email: sviluppo@redturtle.it
License: GPL version 2
Keywords: Python Plone CMS
Classifier: Development Status :: 5 - Production/Stable
Classifier: Environment :: Web Environment
Classifier: Framework :: Plone
Classifier: Framework :: Plone :: Addon
Classifier: Framework :: Plone :: 6.0
Classifier: Programming Language :: Python
Classifier: Programming Language :: Python :: 3.8
Classifier: Programming Language :: Python :: 3.9
Classifier: Programming Language :: Python :: 3.10
Classifier: Programming Language :: Python :: 3.11
Classifier: Operating System :: OS Independent
Classifier: License :: OSI Approved :: GNU General Public License v2 (GPLv2)
Requires-Python: >=3.7
License-File: LICENSE.GPL
License-File: LICENSE.rst
Requires-Dist: setuptools
Requires-Dist: plone.api (>=1.8.4)
Requires-Dist: design.plone.policy
Requires-Dist: souper.plone
Requires-Dist: weasyprint (>=58.1)
Requires-Dist: collective.z3cform.datagridfield (>=3.0.0)
Requires-Dist: collective.exportimport
Provides-Extra: test
Requires-Dist: plone.app.testing ; extra == 'test'
Requires-Dist: plone.testing (>=5.0.0) ; extra == 'test'
Requires-Dist: plone.app.contenttypes ; extra == 'test'
Requires-Dist: plone.app.robotframework[debug] ; extra == 'test'
Requires-Dist: collective.MockMailHost ; extra == 'test'
Requires-Dist: freezegun ; extra == 'test'
Requires-Dist: redturtle.prenotazioni ; extra == 'test'
